Metadata-Version: 2.1
Name: Guildead
Version: 0.0.1
Summary: Guilded RestApi wrapper written in python3
Home-page: https://github.com/Its-Vichy/Guildead
Author: Its_Vichy
Author-email: its_vichy@protonmail.com
License: MIT License
Keywords: guilded rest api
Platform: UNKNOWN
Classifier: Programming Language :: Python
Classifier: Programming Language :: Python :: 2
Classifier: Programming Language :: Python :: 2.7
Classifier: Programming Language :: Python :: 3
Classifier: Programming Language :: Python :: 3.5
Classifier: Programming Language :: Python :: 3.6
Classifier: Programming Language :: Python :: 3.7
Classifier: Programming Language :: Python :: 3.8
Classifier: Programming Language :: Python :: 3.9
Classifier: Programming Language :: Python :: 3.10
